adafruit_atecc/__init__.py
adafruit_atecc/adafruit_atecc.py
adafruit_atecc/adafruit_atecc_asn1.py
adafruit_atecc/adafruit_atecc_cert_util.py
adafruit_circuitpython_atecc-1.3.0.dist-info/licenses/LICENSE
adafruit_circuitpython_atecc-1.3.0.dist-info/METADATA
adafruit_circuitpython_atecc-1.3.0.dist-info/WHEEL
adafruit_circuitpython_atecc-1.3.0.dist-info/top_level.txt
adafruit_circuitpython_atecc-1.3.0.dist-info/RECORD
