Metadata-Version: 2.4
Name: adafruit-circuitpython-atecc
Version: 1.3.0
Summary: Driver for Microchip's ATECCx08 cryptographic co-processors with secure hardware-based key storage
Author-email: Adafruit Industries <circuitpython@adafruit.com>
License: MIT
Project-URL: Homepage, https://github.com/adafruit/Adafruit_CircuitPython_ATECC
Keywords: adafruit,blinka,circuitpython,micropython,atecc,atecc,,microchip,,secure,,element,,key,,co-processor
Classifier: Intended Audience :: Developers
Classifier: Topic :: Software Development :: Libraries
Classifier: Topic :: Software Development :: Embedded Systems
Classifier: Topic :: System :: Hardware
Classifier: License :: OSI Approved :: MIT License
Classifier: Programming Language :: Python :: 3
License-File: LICENSE
Requires-Dist: Adafruit-Blinka
Requires-Dist: adafruit-circuitpython-binascii
Requires-Dist: adafruit-circuitpython-busdevice
Provides-Extra: optional
Dynamic: license-file
